cloudmesh_openapi-4.0.20-py3.9-nspkg.pth
cloudmesh/openapi/__init__.py
cloudmesh/openapi/__version__.py
cloudmesh/openapi/authentication/__init__.py
cloudmesh/openapi/authentication/basic.py
cloudmesh/openapi/command/__init__.py
cloudmesh/openapi/command/openapi.py
cloudmesh/openapi/function/__init__.py
cloudmesh/openapi/function/executor.py
cloudmesh/openapi/function/generator.py
cloudmesh/openapi/function/server.py
cloudmesh/openapi/registry/DataBaseDecorator.py
cloudmesh/openapi/registry/PickleDB.py
cloudmesh/openapi/registry/Registry.py
cloudmesh/openapi/registry/RegistryMongoDB.py
cloudmesh/openapi/registry/RegistryPickle.py
cloudmesh/openapi/registry/__init__.py
cloudmesh/openapi/registry/cache.py
cloudmesh/openapi/registry/fileoperation.py
cloudmesh/openapi/scikitlearn/SklearnGenerator.py
cloudmesh/openapi/scikitlearn/SklearnGeneratorFile.py
cloudmesh/openapi/scikitlearn/__init__.py
tests/__init__.py
tests/repeat.py
tests/test_001_registry.py
tests/test_002_registry_mongo.py
tests/test_003_server_manage_cpu.py
tests/test_010_generator.py
tests/test_011_generator_cpu.py
tests/test_012_generator_calculator.py
tests/test_015_generator_azureai.py
tests/test_020_server_manage.py
tests/test_030_generator_eigenfaces_svm.py
tests/test_server_cms_cpu.py
tests/util.py
tests/generator/LinearRegression.py
tests/generator/LinearRegression_upload-enabled.py
tests/generator/LogisticRegression_JB_cmsoaserver.py
tests/generator/LogisticRegression_Orig.py
tests/generator/LogisticRegression_cmsoaserver.py
tests/generator/RidgeCV.py
tests/generator/RidgeClassifier.py
tests/generator/Sklearngeneratortest.py
tests/generator/Testingpyfileoutput.py
tests/generator/__init__.py
tests/generator/multiple_functions_test2_cmsoaserver.py
tests/generator/sample_function.py
tests/generator/samplefunction_server.py
tests/generator/test_05_generator.py
tests/generator/test_05a_generator.py
tests/lib/__init__.py
tests/lib/generator_test.py
cloudmesh_openapi-4.0.20.dist-info/LICENSE
cloudmesh_openapi-4.0.20.dist-info/METADATA
cloudmesh_openapi-4.0.20.dist-info/WHEEL
cloudmesh_openapi-4.0.20.dist-info/namespace_packages.txt
cloudmesh_openapi-4.0.20.dist-info/top_level.txt
cloudmesh_openapi-4.0.20.dist-info/RECORD
